{
  "author": "kometenstaub",
  "defaultBranch": "main",
  "description": "Prepare data needed by Linked Data Vocabularies.",
  "errors": [],
  "id": "linked-data-helper",
  "lastChangedAt": "2026-07-11T22:02:27.050Z",
  "lastFetchedAt": "2026-07-11T22:02:27.050Z",
  "manifest": {
    "author": "kometenstaub",
    "authorUrl": "https://github.com/kometenstaub",
    "description": "Parse Linked data for Linked Data Vocabularies.",
    "id": "linked-data-helper",
    "isDesktopOnly": true,
    "minAppVersion": "0.12.15",
    "name": "Linked Data Helper",
    "version": "1.0.0"
  },
  "name": "Linked Data Helper",
  "presentInCommunityList": true,
  "releases": [
    {
      "assets": [
        {
          "downloadCount": 3581,
          "name": "main.js",
          "size": 10833
        },
        {
          "downloadCount": 3892,
          "name": "manifest.json",
          "size": 290
        }
      ],
      "author": "github-actions[bot]",
      "description": "# [1.0.0](https://github.com/kometenstaub/linked-data-helper/compare/0.1.8...1.0.0) (2023-04-23)\n\n\n### Bug Fixes\n\n* file writing when folder does not exist ([76836a5](https://github.com/kometenstaub/linked-data-helper/commit/76836a59fe60f85c7b51adeee03ab691541a6e46))\n",
      "downloadCount": 3892,
      "draft": false,
      "name": "1.0.0",
      "prerelease": false,
      "publishedAt": "2023-04-23T11:17:22Z",
      "tag": "1.0.0"
    },
    {
      "assets": [
        {
          "downloadCount": 9,
          "name": "main.js",
          "size": 10789
        },
        {
          "downloadCount": 17,
          "name": "manifest.json",
          "size": 290
        }
      ],
      "author": "github-actions[bot]",
      "description": "## [0.1.8](https://github.com/kometenstaub/linked-data-helper/compare/0.1.7...0.1.8) (2023-04-21)\n\n",
      "downloadCount": 17,
      "draft": false,
      "name": "0.1.8",
      "prerelease": false,
      "publishedAt": "2023-04-21T23:39:35Z",
      "tag": "0.1.8"
    },
    {
      "assets": [
        {
          "downloadCount": 9,
          "name": "main.js",
          "size": 10784
        },
        {
          "downloadCount": 17,
          "name": "manifest.json",
          "size": 290
        }
      ],
      "author": "github-actions[bot]",
      "description": "## [0.1.7](https://github.com/kometenstaub/linked-data-helper/compare/0.1.6...0.1.7) (2023-04-21)\n\n",
      "downloadCount": 17,
      "draft": false,
      "name": "0.1.7",
      "prerelease": false,
      "publishedAt": "2023-04-21T23:38:41Z",
      "tag": "0.1.7"
    },
    {
      "assets": [
        {
          "downloadCount": 8,
          "name": "main.js",
          "size": 9697
        },
        {
          "downloadCount": 18,
          "name": "manifest.json",
          "size": 290
        }
      ],
      "author": "github-actions[bot]",
      "description": "## [0.1.6](https://github.com/kometenstaub/linked-data-helper/compare/0.1.5...0.1.6) (2023-04-21)\n\n",
      "downloadCount": 18,
      "draft": false,
      "name": "0.1.6",
      "prerelease": false,
      "publishedAt": "2023-04-21T23:04:38Z",
      "tag": "0.1.6"
    },
    {
      "assets": [
        {
          "downloadCount": 6,
          "name": "linked-data-helper-0.1.3.zip",
          "size": 4807
        },
        {
          "downloadCount": 13,
          "name": "main.js",
          "size": 9564
        },
        {
          "downloadCount": 20,
          "name": "manifest.json",
          "size": 290
        }
      ],
      "author": "github-actions[bot]",
      "description": "",
      "downloadCount": 20,
      "draft": false,
      "name": "0.1.3",
      "prerelease": false,
      "publishedAt": "2022-07-13T19:35:19Z",
      "tag": "0.1.3"
    },
    {
      "assets": [
        {
          "downloadCount": 11,
          "name": "linked-data-helper-0.1.2.zip",
          "size": 4922
        },
        {
          "downloadCount": 134,
          "name": "main.js",
          "size": 11150
        },
        {
          "downloadCount": 247,
          "name": "manifest.json",
          "size": 290
        }
      ],
      "author": "github-actions[bot]",
      "description": "",
      "downloadCount": 247,
      "draft": false,
      "name": "0.1.2",
      "prerelease": false,
      "publishedAt": "2021-12-20T20:08:32Z",
      "tag": "0.1.2"
    },
    {
      "assets": [
        {
          "downloadCount": 6,
          "name": "linked-data-helper-0.1.1.zip",
          "size": 4806
        },
        {
          "downloadCount": 65,
          "name": "main.js",
          "size": 9719
        },
        {
          "downloadCount": 66,
          "name": "manifest.json",
          "size": 290
        }
      ],
      "author": "github-actions[bot]",
      "description": "",
      "downloadCount": 66,
      "draft": false,
      "name": "0.1.1",
      "prerelease": false,
      "publishedAt": "2021-11-27T11:34:57Z",
      "tag": "0.1.1"
    },
    {
      "assets": [
        {
          "downloadCount": 8,
          "name": "linked-data-helper-0.1.0.zip",
          "size": 4956
        },
        {
          "downloadCount": 13,
          "name": "main.js",
          "size": 10139
        },
        {
          "downloadCount": 15,
          "name": "manifest.json",
          "size": 290
        }
      ],
      "author": "github-actions[bot]",
      "description": "",
      "downloadCount": 15,
      "draft": false,
      "name": "0.1.0",
      "prerelease": false,
      "publishedAt": "2021-11-09T18:43:02Z",
      "tag": "0.1.0"
    },
    {
      "assets": [
        {
          "downloadCount": 6,
          "name": "linked-data-helper-0.0.2.zip",
          "size": 4830
        },
        {
          "downloadCount": 10,
          "name": "main.js",
          "size": 9711
        },
        {
          "downloadCount": 12,
          "name": "manifest.json",
          "size": 290
        }
      ],
      "author": "github-actions[bot]",
      "description": "",
      "downloadCount": 12,
      "draft": false,
      "name": "0.0.2",
      "prerelease": false,
      "publishedAt": "2021-10-30T19:23:48Z",
      "tag": "0.0.2"
    },
    {
      "assets": [
        {
          "downloadCount": 2,
          "name": "linked-data-helper-0.0.1.zip",
          "size": 4830
        },
        {
          "downloadCount": 4,
          "name": "main.js",
          "size": 9711
        },
        {
          "downloadCount": 11,
          "name": "manifest.json",
          "size": 291
        }
      ],
      "author": "github-actions[bot]",
      "description": "",
      "downloadCount": 11,
      "draft": false,
      "name": "0.0.1",
      "prerelease": false,
      "publishedAt": "2021-10-30T19:17:22Z",
      "tag": "0.0.1"
    }
  ],
  "removedAt": null,
  "repo": "kometenstaub/linked-data-helper"
}
