{
  "author": "akaalias",
  "defaultBranch": "master",
  "description": "Discover the story between your notes.",
  "errors": [],
  "id": "obsidian-journey-plugin",
  "lastChangedAt": "2026-06-29T22:02:26.997Z",
  "lastFetchedAt": "2026-06-29T22:02:26.997Z",
  "manifest": {
    "author": "Alexis Rondeau",
    "authorUrl": "https://publish.obsidian.md/alexisrondeau",
    "description": "Discover the stories between your notes.",
    "id": "obsidian-journey-plugin",
    "isDesktopOnly": false,
    "minAppVersion": "0.10.10",
    "name": "Journey",
    "version": "0.0.7"
  },
  "name": "Journey",
  "presentInCommunityList": true,
  "releases": [
    {
      "assets": [
        {
          "downloadCount": 19532,
          "name": "main.js",
          "size": 709740
        },
        {
          "downloadCount": 20669,
          "name": "manifest.json",
          "size": 290
        },
        {
          "downloadCount": 19073,
          "name": "styles.css",
          "size": 2534
        }
      ],
      "author": "akaalias",
      "description": "## Issues Fixed\r\nIcon (simplified) now appears equal on light and dark modes: \r\n\r\n![journey_icon](https://user-images.githubusercontent.com/111555/108209598-c86bb880-712a-11eb-86b1-e6cb510cda38.png)\r\n\r\nFixes: https://github.com/akaalias/obsidian-journey-plugin/issues/7",
      "downloadCount": 20669,
      "draft": false,
      "name": "0.0.7",
      "prerelease": false,
      "publishedAt": "2021-02-17T13:18:01Z",
      "tag": "0.0.7"
    },
    {
      "assets": [
        {
          "downloadCount": 149,
          "name": "main.js",
          "size": 714422
        },
        {
          "downloadCount": 239,
          "name": "manifest.json",
          "size": 290
        },
        {
          "downloadCount": 148,
          "name": "styles.css",
          "size": 2534
        }
      ],
      "author": "akaalias",
      "description": "## New Features\r\n\r\n<img width=\"470\" alt=\"Screenshot 2021-02-15 at 18 12 02\" src=\"https://user-images.githubusercontent.com/111555/107976196-78b9af80-6fb9-11eb-84c2-a452b8cfb9e7.png\">\r\n\r\n### Automatic Linking\r\nIf set, will turn titles in the list into links to their respective note. (Off by default)\r\n\r\nExample output (All note titles are links): \r\n<img width=\"753\" alt=\"Screenshot 2021-02-15 at 18 14 17\" src=\"https://user-images.githubusercontent.com/111555/107976317-a43c9a00-6fb9-11eb-98df-ead090a42362.png\">\r\n\r\n### Automatic Transclusion\r\nIf set, will automatically create transcluding links for you ('![[note]]' instead of '- [[note]]') (Off by default)\r\n\r\nExample output (All links are transcluded): \r\n<img width=\"757\" alt=\"Screenshot 2021-02-15 at 18 14 02\" src=\"https://user-images.githubusercontent.com/111555/107976358-b4ed1000-6fb9-11eb-8daf-c57594806515.png\">\r\n\r\n## Bug Fixes\r\n### Fixes mutated vowel/umlaut-tag problems #6",
      "downloadCount": 239,
      "draft": false,
      "name": "0.0.6",
      "prerelease": false,
      "publishedAt": "2021-02-15T17:16:37Z",
      "tag": "0.0.6"
    },
    {
      "assets": [
        {
          "downloadCount": 366,
          "name": "main.js",
          "size": 708072
        },
        {
          "downloadCount": 460,
          "name": "manifest.json",
          "size": 290
        },
        {
          "downloadCount": 361,
          "name": "styles.css",
          "size": 2534
        }
      ],
      "author": "akaalias",
      "description": "## New Features 🎉\r\nBased on your amazing feedback and ideas, you now have the following new features available:\r\n\r\n### Exclude Folders Feature\r\nAllows you to set a list of comma-separated folder paths (e.g. \"Daily Notes/, Attachments/\") that will be excluded during your search.\r\n\r\n<img width=\"672\" alt=\"Screenshot 2021-02-07 at 15 07 24\" src=\"https://user-images.githubusercontent.com/111555/107148936-34ddff00-6956-11eb-93d1-3119b72674e3.png\">\r\n\r\n### Auto-complete Search Feature\r\nSearch your starting and ending notes by simply starting to type in the name. \r\n\r\n<img width=\"929\" alt=\"Screenshot 2021-02-07 at 15 07 57\" src=\"https://user-images.githubusercontent.com/111555/107148962-563eeb00-6956-11eb-89d5-29948c2aaa47.png\">\r\n\r\n## Communication\r\n### Reporting issues\r\nPlease use https://github.com/akaalias/obsidian-journey-plugin/issues to share bugs and issues you find!\r\n\r\n## Backlog\r\nI've created a public backlog which will allow you to see the progress on features. Prioritisation will come from voting in the group and at my own discretion.\r\n\r\nhttps://trello.com/b/ICKWjoBu/obsidian-journey-plugin-backlog\r\n\r\n![Trello](https://raw.githubusercontent.com/akaalias/obsidian-journey-plugin/master/trello-new.png)\r\n\r\n",
      "downloadCount": 460,
      "draft": false,
      "name": "0.0.5",
      "prerelease": false,
      "publishedAt": "2021-02-07T14:12:53Z",
      "tag": "0.0.5"
    },
    {
      "assets": [
        {
          "downloadCount": 273,
          "name": "main.js",
          "size": 689657
        },
        {
          "downloadCount": 344,
          "name": "manifest.json",
          "size": 290
        },
        {
          "downloadCount": 272,
          "name": "styles.css",
          "size": 2177
        }
      ],
      "author": "akaalias",
      "description": "## New features\r\n- High-contrast results\r\n\r\nBased on [EdElgar](https://forum.obsidian.md/u/edelgar)'s request for higher contrast when reading the result list, you can now toggle on 'high-contrast' in the settings. This will give results in black and white:\r\n\r\n<img width=\"550\" alt=\"Screenshot 2021-02-02 at 14 18 02\" src=\"https://user-images.githubusercontent.com/111555/106605710-830f8e80-6561-11eb-8d45-adc639f8c68e.png\">\r\n\r\n",
      "downloadCount": 344,
      "draft": false,
      "name": "0.0.4",
      "prerelease": false,
      "publishedAt": "2021-02-02T13:18:30Z",
      "tag": "0.0.4"
    },
    {
      "assets": [
        {
          "downloadCount": 119,
          "name": "main.js",
          "size": 686028
        },
        {
          "downloadCount": 197,
          "name": "manifest.json",
          "size": 290
        },
        {
          "downloadCount": 119,
          "name": "styles.css",
          "size": 1602
        }
      ],
      "author": "akaalias",
      "description": "At the heart of it, this plugin finds the journey between two notes in your Obsidian vault. Watch the quick demo below to get an idea:\r\n\r\n[![](https://github.com/akaalias/obsidian-journey-plugin/blob/master/journey-thumbnail.png?raw=true)](https://www.youtube.com/watch?v=iRydNlinRlc)\r\n\r\n### What features are included in this release:\r\n\r\nBased on your feedback and comments, I realized that there are many different ways to go on that journey and so I've created a bunch of features you can toggle on or of to your liking. \r\n\r\nThese features are like preferences you can give your navigation-system in your car. Maybe today, all you care about is getting from A to B quickly. Maybe tomorrow, you have more time to \"take the scenic route.\" I want you to be as flexible as possible.\r\n\r\n- Feature 1: Use \"Forward-Links\" (Enabled by default)\r\n- Feature 2: Use \"Back-Links\" (Enabled by default)\r\n- Feature 3: Using Tags (Disabled by default)\r\n- Feature 4: \"Take the scenic route\" aka Avoid MOCs (Disabled by default)\r\n\r\nBecause each feature has an impact to whether the plugin CAN FIND or CANNOT FIND a path between your two notes, I want to demonstrate what each does as simply as possible. \r\n\r\nSo, let's start by imagining this very basic vault with 4 notes. \"Note A\", \"Note B\", \"Note C\" and \"Note D\"\r\n\r\n- A links to B\r\n- B links to C\r\n- C shares the same tag as D\r\n\r\n![Vault](https://user-images.githubusercontent.com/111555/106387223-0f427a00-63d9-11eb-86b3-5a2ae53a1950.png)\r\n\r\n#### Feature 1: Use \"Forward-Links\" (Enabled by default)\r\nLinks are basically one-way streets from one note to the next. That means the plugin will show you only a path IF a forward-linked path exists but it won't show you a path that goes \"against\" the one-way street. \r\n\r\n![forwardlink](https://user-images.githubusercontent.com/111555/106387228-136e9780-63d9-11eb-84a4-208b308f1b07.png)\r\n\r\nWith the example and this feature turned ON, the plugin will...\r\n\r\n* Successfully find you a path from A to C (Via B) \r\n* NOT find you a path from C to A because that would be against the one-way street\r\n\r\n#### Feature 2: Use \"Back-Links\" (Enabled by default)\r\nThis is basically the inverse of using \"forward-links\". With this feature, you navigation system will find ONLY paths that are based on going against the one-way streets. \r\n\r\n![backlink](https://user-images.githubusercontent.com/111555/106387232-19fd0f00-63d9-11eb-8510-df474ff130d6.png)\r\n\r\n\r\nWith the example and this feature turned ON, the plugin will...\r\n\r\n* NOT find a path from A to C because there are no back-links to follow\r\n* Successfully find you the path from C to A (Via B) because the back-links point that direction\r\n\r\n#### Feature 3: Using Tags (Disabled by default)\r\nThank you [alltagsverstand](https://forum.obsidian.md/u/alltagsverstand/summary) for the idea which I had not thought of and which resonated with many of you.\r\n\r\nAs the name suggests, Tags can now also be paths between notes. \r\n\r\n![tag](https://user-images.githubusercontent.com/111555/106387241-1ff2f000-63d9-11eb-94e2-d62c0995ca17.png)\r\n\r\n\r\nWith the example and this feature turned ON, the plugin will...\r\n\r\n- Successfully find the path from C to D (C -> #tag -> D) and from D to C (D -> #tag -> C)\r\n\r\nIf I now have Back-Links and Forward-Links enabled as well, I can now find the path from:\r\n\r\n- A to D (A -> B -> C -> #tag -> D)\r\n- D to A (D -> #tag -> C -> B -> A)\r\n\r\nNote that this feature is disabled by default.\r\n\r\n#### Feature 4: \"Take the scenic route\" aka Avoid MOCs (Disabled by default)\r\nOne of [thoresson](https://forum.obsidian.md/u/thoresson/summary)'s many ideas that turned out to be really, really useful when I started to pressure-test finding cool paths.\r\n\r\n> Avoid Y (perhaps a tag used for MOC and other structured notes so that only atomic notes are included in the journey)\r\n\r\nIf turned on, this feature will exclude finding a path via MOC notes and help you \"take the scenic route\" instead. With this feature, you avoid passing through the \"big city\" (aka MOC) and instead find a path less traveled. \r\n\r\nIn the following example, with this feature turned ON, the path from A to C would be: \r\n\r\n- A -> Foo -> Bar -> C (instead of A -> MOC -> C)\r\n\r\n![MOC](https://user-images.githubusercontent.com/111555/106387246-26816780-63d9-11eb-9407-a76c078b8e6c.png)\r\n\r\n##### \"How many links make an MOC?\"\r\nA sub-feature for \"taking the scenic route\" where you can define at what amount of links inside a note makes it an MOC to avoid. \r\n\r\nA huge shout-out to [thoresson](https://forum.obsidian.md/u/thoresson), [alltagsverstand](https://forum.obsidian.md/u/alltagsverstand), [Thecookiemomma](https://forum.obsidian.md/u/Thecookiemomma), [cestvrai](https://forum.obsidian.md/u/cestvrai), [matteor](https://forum.obsidian.md/u/matteor), [Danashafir](https://forum.obsidian.md/u/Danashafir), [EhuddRomero](https://forum.obsidian.md/u/EhuddRomero), [I-d-as](https://forum.obsidian.md/u/I-d-as), [osgav](https://forum.obsidian.md/u/osgav), [Erick_James_Dodge](https://forum.obsidian.md/u/Erick_James_Dodge), [3mbry0](https://forum.obsidian.md/u/3mbry0), [Klaas](https://forum.obsidian.md/u/Klaas), [ryanjamurphy](https://forum.obsidian.md/u/ryanjamurphy), [EdElgar](https://forum.obsidian.md/u/EdElgar) and [Daveb08](https://forum.obsidian.md/u/Daveb08) for helping making this awesome for everyone!",
      "downloadCount": 197,
      "draft": false,
      "name": "0.0.3",
      "prerelease": false,
      "publishedAt": "2021-01-31T14:35:08Z",
      "tag": "0.0.3"
    }
  ],
  "removedAt": null,
  "repo": "akaalias/obsidian-journey-plugin"
}
