{
  "author": "jon-heard",
  "defaultBranch": "main",
  "description": "Type text shortcuts which are then replaced with JavaScript generated text.",
  "errors": [],
  "id": "obsidian-text-expander-js",
  "lastChangedAt": "2026-06-01T11:59:01.768Z",
  "lastFetchedAt": "2026-06-01T11:59:01.768Z",
  "manifest": {
    "author": "Jonathan Heard",
    "authorUrl": "https://github.com/jon-heard",
    "description": "Type text shortcuts which are then replaced with JavaScript generated text.",
    "id": "obsidian-text-expander-js",
    "isDesktopOnly": false,
    "minAppVersion": "0.12.0",
    "name": "Inline Scripts",
    "version": "0.24.12"
  },
  "name": "Inline Scripts",
  "presentInCommunityList": true,
  "releases": [
    {
      "assets": [
        {
          "name": "main.js",
          "size": 348375
        },
        {
          "name": "manifest.json",
          "size": 322
        },
        {
          "name": "styles.css",
          "size": 5529
        }
      ],
      "author": "jon-heard",
      "description": "- Plugin updates:\r\n    - bug fix - library version update alert can show up even if it shouldn't\r\n    - feature - shortcut links - remove markdown parsing for shortcut link output (user can do it themselves if necessary)",
      "draft": false,
      "name": "0.24.12",
      "prerelease": false,
      "publishedAt": "2022-12-13T05:17:25Z",
      "tag": "0.24.12"
    },
    {
      "assets": [
        {
          "name": "main.js",
          "size": 348427
        },
        {
          "name": "manifest.json",
          "size": 322
        },
        {
          "name": "styles.css",
          "size": 5529
        }
      ],
      "author": "jon-heard",
      "description": "- Plugin updates\r\n    - feature - helper functions - 3 helper functions added: asyncFilter, asyncMap & asyncForEach.\r\n- Library updates\r\n    - feature - tablefiles - can change multiple table configurations simultaneously by selecting multiple tables with shift or ctrl\r\n    - polish - tablefiles - popup ui layout & styling polished\r\n    - refactor - lists_ui - helper function asyncFilter used instead of internal asyncFilter function.\r\n",
      "draft": false,
      "name": "0.24.11",
      "prerelease": false,
      "publishedAt": "2022-11-14T16:39:52Z",
      "tag": "0.24.11"
    },
    {
      "assets": [
        {
          "name": "main.js",
          "size": 346356
        },
        {
          "name": "manifest.json",
          "size": 322
        },
        {
          "name": "styles.css",
          "size": 5529
        }
      ],
      "author": "jon-heard",
      "description": "- Plugin updates\r\n    - feature - settings - Add alerts when there are updates for the plugin or library\r\n    - feature - helper function - fileWrite (does \"fileCreate\" or \"fileModify\" as appropriate)\r\n    - polish - settings - button-view opening button is disable when button-view is opened\r\n    - polish - settings - moved \"reset settings\" button to \"Actions\" section\r\n    - polish - settings - removed separators between common expansion format settings\r\n- Library updates\r\n    - feature - tablefiles - added an output format: \"array\", which returns a raw array.  Useful for subshortcutting \"tbl roll\"\r\n    - polish - tablefiles - adjusted frontmatter configurations to be pulled from the cache (speeds up \"tbl roll\" popup).\r\n    - feature - readme - added version number\r\n    - bug fix - tablefiles - \"tbl roll\" (non-ui) checks the path against config tables, but not fm-config tables\r\n    - bug fix - tablefiles - table with no configuration is messed up when changing values the first time\r\n",
      "draft": false,
      "name": "0.24.10",
      "prerelease": false,
      "publishedAt": "2022-11-10T15:14:31Z",
      "tag": "0.24.10"
    },
    {
      "assets": [
        {
          "name": "main.js",
          "size": 342166
        },
        {
          "name": "manifest.json",
          "size": 321
        },
        {
          "name": "styles.css",
          "size": 5412
        }
      ],
      "author": "jon-heard",
      "description": "- Plugin updates\r\n    - bug fix - autocomplete - not working when shortcut prefix contains shortcut suffix.\r\n",
      "draft": false,
      "name": "0.24.9",
      "prerelease": false,
      "publishedAt": "2022-11-07T02:11:58Z",
      "tag": "0.24.9"
    },
    {
      "assets": [
        {
          "name": "main.js",
          "size": 342150
        },
        {
          "name": "manifest.json",
          "size": 321
        },
        {
          "name": "styles.css",
          "size": 5412
        }
      ],
      "author": "jon-heard",
      "description": "- Plugin updates\r\n    - feature - readme - properly documented the useful \"unblock()\" help function\r\n    - feature - readme - properly documented an overview of all help functions\r\n    - feature - helperfncs - added helper functions that were around, but not bundled (\"print\", \"runExternal\", \"popups\", \"getSettings\", \"registerView\")\r\n- Library updates\r\n    - feature - tablefiles - table files can contain a frontmatter YAML with their configuration.\r\n    - feature - added confirmations to all \"reset\" shortcuts in the library.  Double-confirmation for \"state\".\r\n",
      "draft": false,
      "name": "0.24.8",
      "prerelease": false,
      "publishedAt": "2022-11-06T15:41:29Z",
      "tag": "0.24.8"
    },
    {
      "assets": [
        {
          "name": "main.js",
          "size": 341661
        },
        {
          "name": "manifest.json",
          "size": 321
        },
        {
          "name": "styles.css",
          "size": 5412
        }
      ],
      "author": "jon-heard",
      "description": "- Plugin updates\r\n    - bug fix - autocomplete - selecting from the list doesn't properly add the selection\r\n    - polish - readme - improved the documentation on \"common format expansion\"\r\n- Library updates\r\n    - bug fix - adventurecrafter - \"themes fill\" is working, but it's output is broken\r\n",
      "draft": false,
      "name": "0.24.7",
      "prerelease": false,
      "publishedAt": "2022-11-05T12:36:45Z",
      "tag": "0.24.7"
    },
    {
      "assets": [
        {
          "name": "main.js",
          "size": 341709
        },
        {
          "name": "manifest.json",
          "size": 321
        },
        {
          "name": "styles.css",
          "size": 5412
        }
      ],
      "author": "jon-heard",
      "description": "- Plugin updates\r\n    - bug fix - If an expansion error throws as null, which SOMEHOW actually happened, it's not being handled well.\r\n- Library updates\r\n    - bug fix - lists - fixed bug with item renaming not recognizing a combo-list variable\r\n",
      "draft": false,
      "name": "0.24.6",
      "prerelease": false,
      "publishedAt": "2022-11-04T19:13:41Z",
      "tag": "0.24.6"
    },
    {
      "assets": [
        {
          "name": "main.js",
          "size": 341522
        },
        {
          "name": "manifest.json",
          "size": 321
        },
        {
          "name": "styles.css",
          "size": 5412
        }
      ],
      "author": "jon-heard",
      "description": "- Plugin updates\r\n    - feature - autocomplete - now shows while typing the shortcut suffix.  This is useful as some shortcut-texts use \":\".\r\n- Library updates\r\n    - feature - tablefiles - registered folders of tables are now pulled recursively.  i.e. If a table is in a subfolder then it will also be pulled.\r\n    - polish - tablefiles - \"tbl roll\" shortcut (non-ui version) now accepts registered table titles and basenames case-insensitively\r\n",
      "draft": false,
      "name": "0.24.5",
      "prerelease": false,
      "publishedAt": "2022-11-04T16:27:00Z",
      "tag": "0.24.5"
    },
    {
      "assets": [
        {
          "name": "main.js",
          "size": 341298
        },
        {
          "name": "manifest.json",
          "size": 321
        },
        {
          "name": "styles.css",
          "size": 5412
        }
      ],
      "author": "jon-heard",
      "description": "- Plugin updates\r\n  - polish - \"ref all\" shortcut removes all horizontal rules in descriptions\r\n  - feature - autocomplete - special types are handled specially:\r\n    - text type highlights indefinitely\r\n    - some of the extra-special types have been converted to text \"text (details)\"\r\n    - number types (>0, >=0) only accept numeric values\r\n    - path text type handles quotes properly (mostly)\r\n- Library updates\r\n    - feature - tablefiles - \"tbl roll\" shortcut (ui-less one) can take the title or basepath of a registered table in addition to a path to a table file.\r\n    - feature - cards - draw and pick now have a variation that allows entering params in any order (using \"from \" & \"to \" prefixes)\r\n    - polish - cards - removed <number OR \"all\"> parameter types.  Lets them work with new type checking, and can just use a really big number for \"all\".\r\n    - polish - updated all syntaxes to better adhere to the newly checked parameter types\r\n",
      "draft": false,
      "name": "0.24.4",
      "prerelease": false,
      "publishedAt": "2022-11-03T14:55:04Z",
      "tag": "0.24.4"
    },
    {
      "assets": [
        {
          "name": "main.js",
          "size": 340820
        },
        {
          "name": "manifest.json",
          "size": 321
        },
        {
          "name": "styles.css",
          "size": 5412
        }
      ],
      "author": "jon-heard",
      "description": "- Plugin updates\r\n  - feature - ShortcutExpander - added event listening for expansion errors\r\n- Library updates\r\n  - added shortcut-file \"system\" - \"sys lasterror\", \"sys runjs\", \"sys triggererror\"\r\n  - polish - une_ui - improved ui.  All shortcuts show one big popup instead of multiple little ones\r\n  - feature - tablefiles - add shortcut \"tbl reroll\"\r\n  - feature - tablefiles - \"tbl roll\" (non-ui version) made parameters case-insensitive\r\n  - feature - tablefiles - \"tbl roll\" (non-ui version) made format parameter flexible\r\n      - removed the need for quotes\r\n      - allowed singular value: \"comma\" instead of commas\"\r\n      - allowed untrimmed value\r\n  - polish - tablefiles - tbl roll (non-ui version) adjusted to be more useful when called from another shortcut\r\n  - feature - tablefiles - \"tbl roll\" shortcut (non-ui version) now accepts a path with implicit \".md\" extension\r\n  - bug fix - tablefiles - tbl roll (non-ui version) errored each time\r\n",
      "draft": false,
      "name": "0.24.3",
      "prerelease": false,
      "publishedAt": "2022-11-03T08:17:50Z",
      "tag": "0.24.3"
    },
    {
      "assets": [
        {
          "name": "main.js",
          "size": 340535
        },
        {
          "name": "manifest.json",
          "size": 321
        },
        {
          "name": "styles.css",
          "size": 5412
        }
      ],
      "author": "jon-heard",
      "description": "- Plugin updates\r\n  - bug fix - shortcutlinks - link doesn't work if part 2 (output script) is included but not defined",
      "draft": false,
      "name": "0.24.2",
      "prerelease": false,
      "publishedAt": "2022-11-02T04:52:21Z",
      "tag": "0.24.2"
    },
    {
      "assets": [
        {
          "name": "main.js",
          "size": 340444
        },
        {
          "name": "manifest.json",
          "size": 321
        },
        {
          "name": "styles.css",
          "size": 5412
        }
      ],
      "author": "jon-heard",
      "description": "- Plugin updates\r\n  - bug fix - append & prepend shortcut links without block-ids are erroring out\r\n  - bug fix - rare race condition causes duplicate buttons in buttons view\r\n- Library updates\r\n  - bug fix - cards - card images don't show when they have spaces or parenthesis\r\n  - bug fix - lists - combo-lists fail\r\n",
      "draft": false,
      "name": "0.24.1",
      "prerelease": false,
      "publishedAt": "2022-11-01T19:26:41Z",
      "tag": "0.24.1"
    },
    {
      "assets": [
        {
          "name": "main.js",
          "size": 340266
        },
        {
          "name": "manifest.json",
          "size": 321
        },
        {
          "name": "styles.css",
          "size": 5412
        }
      ],
      "author": "jon-heard",
      "description": "- Plugin updates\r\n    - \"expFormat()\" adds standard expansion formatting to a string or string array.  This format is based on settings added under \"Expansion format\": prefix, line-prefix and suffix.      - \"expUnformat()\" removes standard expansion formatting from a string or string array.\r\n    - Shortcut links - can include a block-id to define where the output should go\r\n    - Shortcut links - can include a bit of javascript to modify expansion output\r\n    - settings - both the autocomplete feature and the autocomplete help tooltip are togglable in the settings\r\n    - popups.pick - allow turning the dropdown into a list box of either a fixed size, or adaptive size to it's contents\r\n    - popups.custom - \"resolveFnc()\" passed to onOpen to allow early outing with custom result\r\n    - helper function - \"appendToEndOfNote()\" replaced with more versatile \"addToNote()\" function\r\n    - helper function - \"unblock()\" added to manually ublock if the input blocker is left on, such as if a shortcut errors out.\r\n    - helper function - \"getLeafForFile()\" is replaced with \"getLeavesForFile()\"\r\n    - bug fix - the latest Obsidian release breaks some ui in the inline scripts buttons view\r\n- Library updates\r\n    - tablefiles - shortcut-file added!  Allows working with files of tables in different formats.\r\n    - cards 2.0 - a new interface for working with virtual cards.  It has a number of incompatibilities with the older interface.\r\n    - state - state file now saved to same folder as the state shortcut-file.  This ensures the state is properly transferred with the rest of the vault, regardless of what happens to the .obsidian folder.\r\n    - state - state saving is now done after each shortcut is run, rather than on a timer\r\n    - notevars - resolved incompatibilities with latest Obsidian\r\n    - notevars - resolved bug where running \"notevars set\" multiple times only saved one of the changes\r\n    - general - commented entire library\r\n    - general - shortcuts that use pick popups now show lists instead of dropdowns.\r\n    - files - shortcut-file added!  Shortcuts for working with files, including: \"extensionChange\" and \"files shortcutbatch\"\r\n    - lists - added \"lists rename\" and \"lists shortcutbatch\"",
      "draft": false,
      "name": "0.24.0",
      "prerelease": false,
      "publishedAt": "2022-11-01T07:45:34Z",
      "tag": "0.24.0"
    },
    {
      "assets": [
        {
          "name": "main.js",
          "size": 329637
        },
        {
          "name": "manifest.json",
          "size": 321
        },
        {
          "name": "styles.css",
          "size": 5000
        }
      ],
      "author": "jon-heard",
      "description": "- bug fix - state is occasionally not saved on Obsidian quit.",
      "draft": false,
      "name": "0.23.2",
      "prerelease": false,
      "publishedAt": "2022-09-26T14:14:18Z",
      "tag": "0.23.2"
    },
    {
      "assets": [
        {
          "name": "main.js",
          "size": 329658
        },
        {
          "name": "manifest.json",
          "size": 321
        },
        {
          "name": "styles.css",
          "size": 5000
        }
      ],
      "author": "jon-heard",
      "description": "- bug fix - fixed announcement to include \"import latest library\" message.\r\n",
      "draft": false,
      "name": "0.23.1",
      "prerelease": false,
      "publishedAt": "2022-09-26T11:33:36Z",
      "tag": "0.23.1"
    },
    {
      "assets": [
        {
          "name": "main.js",
          "size": 329105
        },
        {
          "name": "manifest.json",
          "size": 321
        },
        {
          "name": "styles.css",
          "size": 5000
        }
      ],
      "author": "jon-heard",
      "description": "- LIBRARY UPDATES\r\n\t- The state system now keeps the state between Obsidian sessions without needing user interaction.\r\n\t- Shortcut added - \"lists fromfile lines {list name} {file name}\" reads a file and adds each of its lines to a list as an item.\r\n\t- Cards system updates:\r\n\t\t- Can modify the cards through the card-pile viewer panel.  Drag to reorder and double-click to rotate.\r\n\t\t- Custom card-backing.\r\n\t\t- Global card size.\r\n\t\t- Can predefine card-piles with the shortcut \"cards pile {pile id}\"\r\n\t\t- Square cards now rotate to any of four directions.  Non-square cards still only rotate to two directions: rightside-up and upside-down.\r\n- PLUGIN\r\n\t- Shortcuts are now case-insensitive (useful for mobile, which auto-cases letters)\r\n\t- \"getObsidianInterfaces\" was merged into \"helperFncs\"\r\n\t- \"onShortcutsLoaded\" event added.\r\n\t- Shutdown scripts are called when closing Obsidian.\r\n\t- The drag-reorder system is improved.\r\n\t- Button panel's create/edit button popup has better field descriptions.\r\n- BUG-FIXES\r\n\t- Card images in notes are absolute, so break when vault is moved or synced.\r\n\t- Drag-reorder not working on mobile.",
      "draft": false,
      "name": "0.23.0",
      "prerelease": false,
      "publishedAt": "2022-09-24T13:06:10Z",
      "tag": "0.23.0"
    },
    {
      "assets": [
        {
          "name": "main.js",
          "size": 325828
        },
        {
          "name": "manifest.json",
          "size": 321
        },
        {
          "name": "styles.css",
          "size": 4639
        }
      ],
      "author": "jon-heard",
      "description": "- LIBRARY UPDATES\r\n\t- Interfacing with the Dice Roller plugin is now possible with the new \"plugin_diceroller\" shortcut-file.\r\n\t\t- This shortcut-file contains a single shortcut `diceroller {command}`\r\n\t- Virtual cards within Obsidian is now available with the new \"cards\" shortcut-file.\r\n\t\t- Check out the tutorial video on the \"cards\" plugin [here](https://www.youtube.com/watch?v=-m4n7d3aKC8)\r\n\t- A new panel type is added to Obisidan to view card-piles with the new \"cards_pileviewer\" shortcut-file.\r\n\t- More user-friendly versions of shortcuts are now available with the \"cards_ui\" shortcut-file.\r\n\t- notepick now uses the state system to save state between Obsidian sessions.\r\n- FEATURES\r\n\t- Functions \"addCss()\" and \"removeCss()\" provided to allow shortcut-files to use their own CSS.  Added to \"window._inlineScripts.inlineScripts.helperFncs\".\r\n\t- Can now customize button texts for popup panels.\r\n\t- popups.input now takes an optional \"suggestions\" array that will show in a dropdown list beneath the textbox (if provided).\r\n\t- Plugin access added at \"window._inlineScripts.inlineScripts.plugin\"\r\n\t- Plugin has getObsidianInterfaces() function that returns some useful Obsidian interfaces.\r\n- BUG-FIXES\r\n\t- In the autocomplete panel, the current parameter isn't highlighted if prior optional parameters were space-skipped.\r\n\t- \"window._inlineScripts\" isn't removed when plugin is disabled",
      "draft": false,
      "name": "0.22.2",
      "prerelease": false,
      "publishedAt": "2022-09-18T16:34:36Z",
      "tag": "0.22.2"
    },
    {
      "assets": [
        {
          "name": "main.js",
          "size": 324909
        },
        {
          "name": "manifest.json",
          "size": 321
        },
        {
          "name": "styles.css",
          "size": 4639
        }
      ],
      "author": "jon-heard",
      "description": "- bug fix - announcement - latest has a broken link.\r\n- polish - announcement - added bullet to announce support shortcut-files.",
      "draft": false,
      "name": "0.22.1",
      "prerelease": false,
      "publishedAt": "2022-09-10T04:28:49Z",
      "tag": "0.22.1"
    },
    {
      "assets": [
        {
          "name": "main.js",
          "size": 324806
        },
        {
          "name": "manifest.json",
          "size": 321
        },
        {
          "name": "styles.css",
          "size": 4639
        }
      ],
      "author": "jon-heard",
      "description": "- Features:\r\n\t- A button panel has been added to plugin, allowing custom button creation for running shortcuts\r\n\t\t- Button panel buttons can run shortcuts with \"???\" run-time parameters\r\n\t\t- Button panel groups allow setting up groups of buttons for different tasks\r\n\t\t- Shortcut-files automatically get their own button panel groups\r\n\t- Shortcut links\r\n\t\t- Links that will trigger a shortcut on clicked, either once or on each click.\r\n\t\t- Can define run-time parameter captions in the link\r\n\t- A number of shortcut-files in the library have been given supplement shortcut-files (\"X_ui.sfile\") to replace certain shortcuts with more graphical versions.\r\n\t- Global variable setup in shortcut-files has been streamlined with the addition of \"confirmObjectPath()\"\r\n\t- Added video tutorials for a number of shortcut-files in the library.\r\n\t- Added a variable with list of the loaded shortcut-files and their registered order.\r\n\t- Made a collection of helper functions available to shortcuts\r\n- Breaking changes:\r\n\t- About string syntax - parameters no longer include \"required\" or \"optional\".\r\n\t\t- \"Optional\" parameters are now any parameters that specify a default value.\r\n\t- The variable where session state is stored has changed location:\r\n\t\t- It has moved from \"_inlineScripts.state\" to \"_inlineScripts.state.sessionState\"\r\n\t- In the library, the new \"x_ui\" suppliment shortcut-files redo some of the more complex shortcuts.  It's possible that this may cause some confusion, if the user isn't aware of them.\r\n- Changes:\r\n\t- Startup and shutdown scripts can now use helper scripts\r\n\t- Warning added when shortcut-file is registered, but has no shortcuts\r\n\t- Can display multiple version annoucements when plugin is updated\r\n\t- Buymecoffee donation method added.  Donation methods added to bottom of settings.",
      "draft": false,
      "name": "0.22.0",
      "prerelease": false,
      "publishedAt": "2022-09-10T04:27:16Z",
      "tag": "0.22.0"
    }
  ],
  "removedAt": null,
  "repo": "jon-heard/obsidian-inline-scripts"
}
